jax_tpu_embedding/__init__.py
jax_tpu_embedding/prebuilt.cpython-313-x86_64-linux-gnu.so
jax_tpu_embedding/sparsecore/__init__.py
jax_tpu_embedding/sparsecore/version.py
jax_tpu_embedding/sparsecore/lib/__init__.py
jax_tpu_embedding/sparsecore/lib/auto_pipelining/__init__.py
jax_tpu_embedding/sparsecore/lib/auto_pipelining/auto_pipelining.py
jax_tpu_embedding/sparsecore/lib/auto_pipelining/decompose.py
jax_tpu_embedding/sparsecore/lib/auto_pipelining/preprocess.py
jax_tpu_embedding/sparsecore/lib/auto_pipelining/utils.py
jax_tpu_embedding/sparsecore/lib/core/__init__.py
jax_tpu_embedding/sparsecore/lib/core/constants.py
jax_tpu_embedding/sparsecore/lib/core/input_preprocessing.py
jax_tpu_embedding/sparsecore/lib/core/libinput_preprocessing_core.so
jax_tpu_embedding/sparsecore/lib/core/libinput_preprocessing_threads.so
jax_tpu_embedding/sparsecore/lib/core/libinput_preprocessing_util.so
jax_tpu_embedding/sparsecore/lib/core/pybind_input_preprocessing.so
jax_tpu_embedding/sparsecore/lib/core/primitives/__init__.py
jax_tpu_embedding/sparsecore/lib/core/primitives/optimizers_computation.py
jax_tpu_embedding/sparsecore/lib/core/primitives/sparse_dense_matmul_csr.py
jax_tpu_embedding/sparsecore/lib/core/primitives/sparse_dense_matmul_grad_with_adagrad.py
jax_tpu_embedding/sparsecore/lib/core/primitives/sparse_dense_matmul_grad_with_adagrad_momentum.py
jax_tpu_embedding/sparsecore/lib/core/primitives/sparse_dense_matmul_grad_with_adam.py
jax_tpu_embedding/sparsecore/lib/core/primitives/sparse_dense_matmul_grad_with_ftrl.py
jax_tpu_embedding/sparsecore/lib/core/primitives/sparse_dense_matmul_grad_with_laprop.py
jax_tpu_embedding/sparsecore/lib/core/primitives/sparse_dense_matmul_grad_with_sgd.py
jax_tpu_embedding/sparsecore/lib/core/primitives/sparse_dense_matmul_optimizer_grad.py
jax_tpu_embedding/sparsecore/lib/core/primitives/utils.py
jax_tpu_embedding/sparsecore/lib/fdo/__init__.py
jax_tpu_embedding/sparsecore/lib/fdo/fdo_client.py
jax_tpu_embedding-0.1.0.dev20251016.dist-info/METADATA
jax_tpu_embedding-0.1.0.dev20251016.dist-info/WHEEL
jax_tpu_embedding-0.1.0.dev20251016.dist-info/top_level.txt
jax_tpu_embedding-0.1.0.dev20251016.dist-info/RECORD
jax_tpu_embedding-0.1.0.dev20251016.dist-info/licenses/LICENSE
