Metadata-Version: 2.4
Name: jax_tpu_embedding
Version: 0.1.0.dev20251016
Summary: JAX SparseCore API
Author-email: JAX SC Authors <jax-sc-dev@google.com>
License: 
Project-URL: homepage, https://github.com/jax-ml/jax_tpu_embedding
Project-URL: repository, https://github.com/jax-ml/jax_tpu_embedding
Classifier: License :: OSI Approved :: Apache Software License
Classifier: Intended Audience :: Science/Research
Classifier: Programming Language :: Python :: 3.10
Classifier: Programming Language :: Python :: 3.11
Classifier: Programming Language :: Python :: 3.12
Classifier: Programming Language :: Python :: 3.13
Requires-Python: >=3.10
License-File: LICENSE
Requires-Dist: absl-py
Requires-Dist: einops
Requires-Dist: flax
Requires-Dist: jax
Requires-Dist: numpy
Requires-Dist: portpicker
Dynamic: license-file
